[
    {
        "name": "Ajay Mehta",
        "capgId": "183440",
        "capgEmail": "ajay.a.mehta@capgemini.com",
        "bu":"Bu",
        "shadowProjectName":"shadowProjectName",
        "shadowProjectMentor":"shadowProjectMentor",
        "date":"20-03-20",
        "taskDescription": "taskDescription"
    },
    {
        "name": "Abhishek ",
        "capgId": "183441",
        "capgEmail": "Abhishek.a.Abhishek@capgemini.com",
        "bu":"Bu",
        "shadowProjectName":"shadowProjectName",
        "shadowProjectMentor":"shadowProjectMentor",
        "date":"20-03-20",
        "taskDescription": "taskDescription"
    },
    {
        "name": "John ",
        "capgId": "183442",
        "capgEmail": "John.a.John@capgemini.com",
        "bu":"Bu",
        "shadowProjectName":"shadowProjectName",
        "shadowProjectMentor":"shadowProjectMentor",
        "date":"20-03-20",
        "taskDescription": "taskDescription"
    }
]